hachi64/__init__.py
hachi64-0.1.3.dist-info/METADATA
hachi64-0.1.3.dist-info/WHEEL
hachi64-0.1.3.dist-info/top_level.txt
hachi64-0.1.3.dist-info/RECORD
