Metadata-Version: 2.4
Name: hachi64
Version: 0.1.3
Summary: A library for custom Base64 encoding and decoding.
Home-page: https://github.com/fengb3/hachi64
Author: Your Name
Author-email: your.email@example.com
Classifier: Programming Language :: Python :: 3
Classifier: License :: OSI Approved :: MIT License
Classifier: Operating System :: OS Independent
Requires-Python: >=3.6
Dynamic: author
Dynamic: author-email
Dynamic: classifier
Dynamic: description
Dynamic: description-content-type
Dynamic: home-page
Dynamic: requires-python
Dynamic: summary
